bixor/__init__.py
bixor-1.0.4.dist-info/METADATA
bixor-1.0.4.dist-info/WHEEL
bixor-1.0.4.dist-info/top_level.txt
bixor-1.0.4.dist-info/RECORD
