Metadata-Version: 2.1
Name: bixor
Version: 1.0.4
Summary: Bixor allows you to encrypt strings with Binary Xor.
Home-page: https://github.com/lactua/bixor
Author: Lactua
Author-email: minedrayxio@gmail.com
Project-URL: Bug Tracker, https://github.com/lactua/bixor/issues
Classifier: Programming Language :: Python :: 3
Classifier: License :: OSI Approved :: MIT License
Classifier: Operating System :: OS Independent
Requires-Python: >=3.6
